junction/__init__.py
junction/cli.py
junction/confluence/__init__.py
junction/confluence/api/__init__.py
junction/confluence/api/content_api.py
junction/confluence/models/__init__.py
junction/confluence/models/json.py
junction/confluence/models/subclassing.py
junction/delta.py
junction/git/__init__.py
junction/image_attachment.py
junction/markdown/__init__.py
junction/markdown/checklists.py
junction/markdown/children.py
junction/markdown/codeblocks.py
junction/markdown/grid_tables.py
junction/markdown/image.py
junction/markdown/info_panels.py
junction/markdown/mermaid.py
junction/markdown/status.py
junction/markdown/toc.py
junction/markdown/wiki_links.py
junction/mermaid_renderer.py
junction/util.py
annalise_confluence_junction-2.0.0.dist-info/entry_points.txt
annalise_confluence_junction-2.0.0.dist-info/METADATA
annalise_confluence_junction-2.0.0.dist-info/WHEEL
annalise_confluence_junction-2.0.0.dist-info/RECORD
