Metadata-Version: 2.1
Name: annalise-confluence-junction
Version: 2.0.0
Summary: Publish to and manage Confluence spaces with markdown files tracked in Git.
Home-page: https://github.com/HUU/Junction
License: MIT
Keywords: confluence,markdown,git,sync,convert
Author: Lachlan Newman
Author-email: lachnewman007@gmail.com
Requires-Python: >=3.8.0,<3.9.0
Classifier: License :: OSI Approved :: MIT License
Classifier: Programming Language :: Python :: 3
Classifier: Programming Language :: Python :: 3.8
Requires-Dist: CairoSVG (>=2.5.2,<3.0.0)
Requires-Dist: Faker (>=13.15.1,<14.0.0)
Requires-Dist: click (==8.1.3)
Requires-Dist: click-log (>=0.3.2,<0.4.0)
Requires-Dist: colorama (>=0.4.3,<0.5.0)
Requires-Dist: gitpython (>=3.0.5,<4.0.0)
Requires-Dist: markdown (>=3.0.1,<4.0.0)
Requires-Dist: markdown-emdash (>=0.1.0,<0.2.0)
Requires-Dist: markdown-urlize (>=0.2.0,<0.3.0)
Requires-Dist: markdownsubscript (>=2.1.1,<3.0.0)
Requires-Dist: markdownsuperscript (>=2.1.1,<3.0.0)
Requires-Dist: pyppeteer (>=1.0.2,<2.0.0)
Requires-Dist: pytest-mock (>=3.8.2,<4.0.0)
Requires-Dist: python-magic (==0.4.27)
Requires-Dist: requests (>=2.22.0,<3.0.0)
Project-URL: Repository, https://github.com/HUU/Junction
